pyqrack/__init__.py
pyqrack/neuron_activation_fn.py
pyqrack/pauli.py
pyqrack/qrack_circuit.py
pyqrack/qrack_neuron.py
pyqrack/qrack_simulator.py
pyqrack/quimb_circuit_type.py
pyqrack/qrack_cl_precompile/Linux/2_35/qrack_cl_precompile
pyqrack/qrack_system/__init__.py
pyqrack/qrack_system/qrack_system.py
pyqrack/qrack_system/qrack_lib/Linux/2_35/libqrack.a
pyqrack/qrack_system/qrack_lib/Linux/2_35/libqrack_pinvoke.so
pyqrack/qrack_system/qrack_lib/Linux/2_35/libqrack_pinvoke.so.9.6.0
pyqrack/util/__init__.py
pyqrack/util/convert_qiskit_circuit_to_qasm_experiment.py
pyqrack_cuda-1.27.0.dist-info/LICENSE
pyqrack_cuda-1.27.0.dist-info/METADATA
pyqrack_cuda-1.27.0.dist-info/WHEEL
pyqrack_cuda-1.27.0.dist-info/top_level.txt
pyqrack_cuda-1.27.0.dist-info/RECORD
