Metadata-Version: 2.1
Name: pyqrack-cuda
Version: 1.27.0
Summary: pyqrack - Pure Python vm6502q/qrack Wrapper
Home-page: https://github.com/vm6502q/pyqrack
Author: Daniel Strano
Author-email: dan@unitary.fund
License: MIT
Keywords: pyqrack qrack simulator quantum gpu
Classifier: Environment :: Console
Classifier: Intended Audience :: Developers
Classifier: Intended Audience :: Science/Research
Classifier: Operating System :: Microsoft :: Windows
Classifier: Operating System :: MacOS
Classifier: Operating System :: POSIX :: Linux
Classifier: Programming Language :: C++
Classifier: Programming Language :: Python :: 3.5
Classifier: Programming Language :: Python :: 3.6
Classifier: Programming Language :: Python :: 3.7
Classifier: Programming Language :: Python :: 3.8
Classifier: Programming Language :: Python :: 3.9
Classifier: Programming Language :: Python :: 3.10
Classifier: Topic :: Scientific/Engineering
License-File: LICENSE
Provides-Extra: dev
Requires-Dist: pytest (>=7.3.1) ; extra == 'dev'
